[
{"kp":"VDA","w":"V","d":"abgewöhnen (D. + A.)"},
{"kp":"VDA","w":"V","d":"angewöhnen (D. + A.)"},
{"kp":"VDA","w":"V","d":"anbieten (D. + A.)"},
{"kp":"VDA","w":"V","d":"auffallen (D. + A.)"},
{"kp":"VDA","w":"V","d":"beschreiben (D. + A.)"},
{"kp":"VDA","w":"V","d":"bestätigen (D. + A.)"},
{"kp":"VDA","w":"V","d":"bieten (D. + A.)"},
{"kp":"VDA","w":"V","d":"borgen (D. + A.)"},
{"kp":"VDA","w":"V","d":"bringen (D. + A.)"},
{"kp":"VDA","w":"V","d":"empfehlen (D. + A.)"},
{"kp":"VDA","w":"V","d":"entziehen (D. + A.)"},
{"kp":"VDA","w":"V","d":"erklären (D. + A.)"},
{"kp":"VDA","w":"V","d":"erlauben (D. + A.)"},
{"kp":"VDA","w":"V","d":"erleichtern (D. + A.)"},
{"kp":"VDA","w":"V","d":"ermöglichen (D. + A.)"},
{"kp":"VDA","w":"V","d":"erzählen (D. + A.)"},
{"kp":"VDA","w":"V","d":"geben (D. + A.)"},
{"kp":"VDA","w":"V","d":"gestatten (D. + A.)"},
{"kp":"VDA","w":"V","d":"glauben (D. + A.)"},
{"kp":"VDA","w":"V","d":"leihen (D. + A.)"},
{"kp":"VDA","w":"V","d":"liefern (D. + A.)"},
{"kp":"VDA","w":"V","d":"mitteilen (D. + A.)"},
{"kp":"VDA","w":"V","d":"nennen (D. + A.)"},
{"kp":"VDA","w":"V","d":"präsentieren (D. + A.)"},
{"kp":"VDA","w":"V","d":"schenken (D. + A.)"},
{"kp":"VDA","w":"V","d":"schicken (D. + A.)"},
{"kp":"VDA","w":"V","d":"schreiben (D. + A.)"},
{"kp":"VDA","w":"V","d":"schulden (D. + A.)"},
{"kp":"VDA","w":"V","d":"senden (D. + A.)"},
{"kp":"VDA","w":"V","d":"servieren (D. + A.)"},
{"kp":"VDA","w":"V","d":"spenden (D. + A.)"},
{"kp":"VDA","w":"V","d":"verbieten (D. + A.)"},
{"kp":"VDA","w":"V","d":"verdanken (D. + A.)"},
{"kp":"VDA","w":"V","d":"verheimlichen (D. + A.)"},
{"kp":"VDA","w":"V","d":"verkaufen (D. + A.)"},
{"kp":"VDA","w":"V","d":"vermitteln (D. + A.)"},
{"kp":"VDA","w":"V","d":"verraten (D. + A.)"},
{"kp":"VDA","w":"V","d":"verschweigen (D. + A.)"},
{"kp":"VDA","w":"V","d":"versprechen (D. + A.)"},
{"kp":"VDA","w":"V","d":"verzeihen (D. + A.)"},
{"kp":"VDA","w":"V","d":"vorlesen (D. + A.)"},
{"kp":"VDA","w":"V","d":"vorschlagen (D. + A.)"},
{"kp":"VDA","w":"V","d":"wegnehmen (D. + A.)"},
{"kp":"VDA","w":"V","d":"wiedergeben (D. + A.)"},
{"kp":"VDA","w":"V","d":"wünschen (D. + A.)"},
{"kp":"VDA","w":"V","d":"zeigen (D. + A.)"},
{"kp":"VDA","w":"V","d":"zuordnen (D. + A.)"},
{"kp":"VDA","w":"V","d":"zurückbringen (D. + A.)"}
]
